vitalx/aggregation/__init__.py
vitalx/aggregation/auth_utils.py
vitalx/aggregation/dsl.py
vitalx/aggregation/executor.py
vitalx/aggregation/polars.py
vitalx/aggregation/types.py
vitalx_aggregation-0.3.0.dist-info/WHEEL
vitalx_aggregation-0.3.0.dist-info/LICENSE.txt
vitalx_aggregation-0.3.0.dist-info/METADATA
vitalx_aggregation-0.3.0.dist-info/RECORD
