Metadata-Version: 2.1
Name: vitalx-aggregation
Version: 0.3.0
Summary: Vital Horizon AI Aggregation API
Home-page: https://www.tryvital.com/
License: AGPL-3.0-only
Author: Vital
Author-email: developers@tryvital.io
Requires-Python: >=3.11,<4.0
Classifier: Development Status :: 4 - Beta
Classifier: Intended Audience :: Developers
Classifier: Intended Audience :: Science/Research
Classifier: License :: OSI Approved :: GNU Affero General Public License v3
Classifier: Programming Language :: Python :: 3
Classifier: Programming Language :: Python :: 3.11
Classifier: Topic :: Scientific/Engineering
Classifier: Topic :: Scientific/Engineering :: Artificial Intelligence
Classifier: Topic :: Software Development
Provides-Extra: cli-auth
Requires-Dist: polars (>=1.5,<2.0)
Requires-Dist: pydantic (>=2.0,<3.0)
Requires-Dist: requests (>=2.32,<3.0)
Requires-Dist: vitalx-cli-auth (<1.0) ; extra == "cli-auth"
Requires-Dist: vitalx-types (<1.0)
Project-URL: Documentation, https://docs.tryvital.io/
